[{"activity_title":"Mountain", "description":"Bla Bla Bla Bla bla bla bla bla bla bla bla bla bla bla bla bla"
, "target_age_group_left": 13, "target_age_group_right": 17, "img_url": "https://cdn.quasar.dev/img/mountains.jpg"}, 
{"activity_title":"Lake", "description":"Bla Bla Bla Bla bla bla bla bla bla bla bla bla bla bla bla bla"
, "target_age_group_left": 6, "target_age_group_right": 8, "img_url":"https://cdn.quasar.dev/img/parallax1.jpg"},
{"activity_title":"Mountain", "description":"Bla Bla Bla Bla bla bla bla bla bla bla bla bla bla bla bla bla"
, "target_age_group_left": 13, "target_age_group_right": 17, "img_url": "https://cdn.quasar.dev/img/mountains.jpg"},
{"activity_title":"Lake", "description":"Bla Bla Bla Bla bla bla bla bla bla bla bla bla bla bla bla bla"
, "target_age_group_left": 6, "target_age_group_right": 8, "img_url":"https://cdn.quasar.dev/img/parallax1.jpg"},
{"activity_title":"Bridge", "description":"Bla Bla Bla Bla bla bla bla bla bla bla bla bla bla bla bla bla"
, "target_age_group_left": 6, "target_age_group_right": 8, "img_url":"https://cdn.quasar.dev/img/parallax2.jpg"},
{"activity_title":"Bridge", "description":"Bla Bla Bla Bla bla bla bla bla bla bla bla bla bla bla bla bla"
, "target_age_group_left": 6, "target_age_group_right": 8, "img_url":"https://cdn.quasar.dev/img/parallax2.jpg"},
{"activity_title":"Bridge", "description":"Bla Bla Bla Bla bla bla bla bla bla bla bla bla bla bla bla bla"
, "target_age_group_left": 6, "target_age_group_right": 8, "img_url":"https://cdn.quasar.dev/img/parallax2.jpg"},
{"activity_title":"Bridge", "description":"Bla Bla Bla Bla bla bla bla bla bla bla bla bla bla bla bla bla"
, "target_age_group_left": 6, "target_age_group_right": 8, "img_url":"https://cdn.quasar.dev/img/parallax2.jpg"},
{"activity_title":"Bridge", "description":"Bla Bla Bla Bla bla bla bla bla bla bla bla bla bla bla bla bla"
, "target_age_group_left": 6, "target_age_group_right": 8, "img_url":"https://cdn.quasar.dev/img/parallax2.jpg"},
{"activity_title":"Bridge", "description":"Bla Bla Bla Bla bla bla bla bla bla bla bla bla bla bla bla bla"
, "target_age_group_left": 6, "target_age_group_right": 8, "img_url":"https://cdn.quasar.dev/img/parallax2.jpg"},
{"activity_title":"Bridge", "description":"Bla Bla Bla Bla bla bla bla bla bla bla bla bla bla bla bla bla"
, "target_age_group_left": 6, "target_age_group_right": 8, "img_url":"https://cdn.quasar.dev/img/parallax2.jpg"},
{"activity_title":"Bridge", "description":"Bla Bla Bla Bla bla bla bla bla bla bla bla bla bla bla bla bla"
, "target_age_group_left": 6, "target_age_group_right": 8, "img_url":"https://cdn.quasar.dev/img/parallax2.jpg"},
{"activity_title":"Mountain", "description":"Bla Bla Bla Bla bla bla bla bla bla bla bla bla bla bla bla bla"
, "target_age_group_left": 13, "target_age_group_right": 17, "img_url": "https://cdn.quasar.dev/img/mountains.jpg"}, 
{"activity_title":"Lake", "description":"Bla Bla Bla Bla bla bla bla bla bla bla bla bla bla bla bla bla"
, "target_age_group_left": 6, "target_age_group_right": 8, "img_url":"https://cdn.quasar.dev/img/parallax1.jpg"},
{"activity_title":"Mountain", "description":"Bla Bla Bla Bla bla bla bla bla bla bla bla bla bla bla bla bla"
, "target_age_group_left": 13, "target_age_group_right": 17, "img_url": "https://cdn.quasar.dev/img/mountains.jpg"},
{"activity_title":"Lake", "description":"Bla Bla Bla Bla bla bla bla bla bla bla bla bla bla bla bla bla"
, "target_age_group_left": 6, "target_age_group_right": 8, "img_url":"https://cdn.quasar.dev/img/parallax1.jpg"}
]